{
  "main": {
    "id": "2e8b919f0c7ac175",
    "type": "split",
    "children": [
      {
        "id": "81c6a63630f98aff",
        "type": "tabs",
        "children": [
          {
            "id": "48be642fa7c3e26e",
            "type": "leaf",
            "state": {
              "type": "markdown",
              "state": {
                "file": "readme.md",
                "mode": "source",
                "source": false
              },
              "icon": "lucide-file",
              "title": "readme"
            }
          }
        ]
      }
    ],
    "direction": "vertical"
  },
  "left": {
    "id": "76438ba86afd7391",
    "type": "split",
    "children": [
      {
        "id": "288e608581f0f5ea",
        "type": "tabs",
        "children": [
          {
            "id": "1192271228f60e2b",
            "type": "leaf",
            "state": {
              "type": "file-explorer",
              "state": {
                "sortOrder": "alphabetical",
                "autoReveal": false
              },
              "icon": "lucide-folder-closed",
              "title": "文件列表"
            }
          },
          {
            "id": "79b4aa8b0f96e32c",
            "type": "leaf",
            "state": {
              "type": "search",
              "state": {
                "query": "",
                "matchingCase": false,
                "explainSearch": false,
                "collapseAll": false,
                "extraContext": false,
                "sortOrder": "alphabetical"
              },
              "icon": "lucide-search",
              "title": "搜索"
            }
          },
          {
            "id": "1882afdb8bedba1d",
            "type": "leaf",
            "state": {
              "type": "bookmarks",
              "state": {},
              "icon": "lucide-bookmark",
              "title": "书签"
            }
          }
        ]
      }
    ],
    "direction": "horizontal",
    "width": 300
  },
  "right": {
    "id": "5c4d0f0710c5f293",
    "type": "split",
    "children": [
      {
        "id": "2e2ce868f2328f23",
        "type": "tabs",
        "children": [
          {
            "id": "29177870991c6881",
            "type": "leaf",
            "state": {
              "type": "backlink",
              "state": {
                "file": "readme.md",
                "collapseAll": false,
                "extraContext": false,
                "sortOrder": "alphabetical",
                "showSearch": false,
                "searchQuery": "",
                "backlinkCollapsed": false,
                "unlinkedCollapsed": true
              },
              "icon": "links-coming-in",
              "title": "readme 的反向链接列表"
            }
          },
          {
            "id": "4e82283eeea5aacb",
            "type": "leaf",
            "state": {
              "type": "outgoing-link",
              "state": {
                "file": "readme.md",
                "linksCollapsed": false,
                "unlinkedCollapsed": true
              },
              "icon": "links-going-out",
              "title": "readme 的出链列表"
            }
          },
          {
            "id": "2169873a3338e071",
            "type": "leaf",
            "state": {
              "type": "tag",
              "state": {
                "sortOrder": "frequency",
                "useHierarchy": true,
                "showSearch": false,
                "searchQuery": ""
              },
              "icon": "lucide-tags",
              "title": "标签"
            }
          },
          {
            "id": "8b1cbbf0baa6c218",
            "type": "leaf",
            "state": {
              "type": "all-properties",
              "state": {
                "sortOrder": "frequency",
                "showSearch": false,
                "searchQuery": ""
              },
              "icon": "lucide-archive",
              "title": "添加笔记属性"
            }
          },
          {
            "id": "18ed405dcbb13d0b",
            "type": "leaf",
            "state": {
              "type": "outline",
              "state": {
                "file": "readme.md",
                "followCursor": false,
                "showSearch": false,
                "searchQuery": ""
              },
              "icon": "lucide-list",
              "title": "readme 的大纲"
            }
          }
        ]
      }
    ],
    "direction": "horizontal",
    "width": 300,
    "collapsed": true
  },
  "left-ribbon": {
    "hiddenItems": {
      "switcher:打开快速切换": false,
      "graph:查看关系图谱": false,
      "canvas:新建白板": false,
      "daily-notes:打开/创建今天的日记": false,
      "templates:插入模板": false,
      "command-palette:打开命令面板": false,
      "bases:新建数据库": false
    }
  },
  "active": "48be642fa7c3e26e",
  "lastOpenFiles": []
}